KubernetesZhinan/README.md
KubernetesZhinan/__init__.py
KubernetesZhinan/__main__.py
KubernetesZhinan/file.epub
KubernetesZhinan/index.html
KubernetesZhinan/css/__init__.py
KubernetesZhinan/css/annotations.css
KubernetesZhinan/css/main.css
KubernetesZhinan/css/normalize.css
KubernetesZhinan/css/popup.css
KubernetesZhinan/font/__init__.py
KubernetesZhinan/font/fontello.eot
KubernetesZhinan/font/fontello.svg
KubernetesZhinan/font/fontello.ttf
KubernetesZhinan/font/fontello.woff
KubernetesZhinan/img/__init__.py
KubernetesZhinan/img/annotator-glyph-sprite.png
KubernetesZhinan/img/annotator-icon-sprite.png
KubernetesZhinan/img/apple-touch-icon.png
KubernetesZhinan/img/cancelfullscreen.png
KubernetesZhinan/img/close.png
KubernetesZhinan/img/fullscreen.png
KubernetesZhinan/img/loader.gif
KubernetesZhinan/img/menu-icon.png
KubernetesZhinan/img/save.png
KubernetesZhinan/img/saved.png
KubernetesZhinan/img/settings-s.png
KubernetesZhinan/img/settings.png
KubernetesZhinan/img/star.png
KubernetesZhinan/js/__init__.py
KubernetesZhinan/js/epub.js
KubernetesZhinan/js/epub.min.js
KubernetesZhinan/js/epub.min.map
KubernetesZhinan/js/hooks.min.js
KubernetesZhinan/js/hooks.min.map
KubernetesZhinan/js/reader.js
KubernetesZhinan/js/reader.js.map
KubernetesZhinan/js/reader.min.js
KubernetesZhinan/js/reader.min.map
KubernetesZhinan/js/hooks/__init__.py
KubernetesZhinan/js/hooks/extensions/__init__.py
KubernetesZhinan/js/hooks/extensions/highlight.js
KubernetesZhinan/js/libs/__init__.py
KubernetesZhinan/js/libs/jquery.min.js
KubernetesZhinan/js/libs/localforage.min.js
KubernetesZhinan/js/libs/screenfull.js
KubernetesZhinan/js/libs/screenfull.min.js
KubernetesZhinan/js/libs/zip.min.js
KubernetesZhinan/js/plugins/__init__.py
KubernetesZhinan/js/plugins/hypothesis.js
KubernetesZhinan/js/plugins/search.js
kubernetes_zhinan-2024.3.3.0.dist-info/METADATA
kubernetes_zhinan-2024.3.3.0.dist-info/WHEEL
kubernetes_zhinan-2024.3.3.0.dist-info/entry_points.txt
kubernetes_zhinan-2024.3.3.0.dist-info/top_level.txt
kubernetes_zhinan-2024.3.3.0.dist-info/RECORD
